xcomstorage/__init__.py
xcomstorage/conf/__init__.py
xcomstorage/conf/xcom.py
xcomstorage/storage/__init__.py
xcomstorage/storage/xcom.py
xcomstorage/xcom.py
xcomstorage-0.1.1.dist-info/METADATA
xcomstorage-0.1.1.dist-info/WHEEL
xcomstorage-0.1.1.dist-info/RECORD
