Metadata-Version: 2.1
Name: XcomStorage
Version: 0.1.1
Summary: xflow xcom storage
Author: hanoch
Requires-Python: >=3.11,<4.0
Classifier: Programming Language :: Python :: 3
Classifier: Programming Language :: Python :: 3.11
Classifier: Programming Language :: Python :: 3.12
Requires-Dist: minio (==7.2.0)
Requires-Dist: pydantic (==2.3.0)
Requires-Dist: pydantic-settings (==2.1.0)
Requires-Dist: redis (==5.0.0)
